odoo10_addon_sale_automatic_workflow_payment_ref-10.0.1.0.1-nspkg.pth
odoo/addons/sale_automatic_workflow_payment_ref/README.rst
odoo/addons/sale_automatic_workflow_payment_ref/__init__.py
odoo/addons/sale_automatic_workflow_payment_ref/__manifest__.py
odoo/addons/sale_automatic_workflow_payment_ref/i18n/sale_automatic_workflow_payment_ref.pot
odoo/addons/sale_automatic_workflow_payment_ref/models/__init__.py
odoo/addons/sale_automatic_workflow_payment_ref/models/automatic_workflow_job.py
odoo/addons/sale_automatic_workflow_payment_ref/static/description/icon.png
odoo/addons/sale_automatic_workflow_payment_ref/tests/__init__.py
odoo/addons/sale_automatic_workflow_payment_ref/tests/test_automatic_workflow_job.py
odoo10_addon_sale_automatic_workflow_payment_ref-10.0.1.0.1.dist-info/METADATA
odoo10_addon_sale_automatic_workflow_payment_ref-10.0.1.0.1.dist-info/WHEEL
odoo10_addon_sale_automatic_workflow_payment_ref-10.0.1.0.1.dist-info/namespace_packages.txt
odoo10_addon_sale_automatic_workflow_payment_ref-10.0.1.0.1.dist-info/top_level.txt
odoo10_addon_sale_automatic_workflow_payment_ref-10.0.1.0.1.dist-info/RECORD
