Metadata-Version: 2.1
Name: odoo10-addon-sale-automatic-workflow-payment-ref
Version: 10.0.1.0.1
Summary: Propagates your payment reference from your sale order to your payment
Home-page: https://github.com/OCA/sale-workflow
Author: ACSONE SA/NV,Odoo Community Association (OCA)
Author-email: support@odoo-community.org
License: AGPL-3
Platform: UNKNOWN
Classifier: Programming Language :: Python
Classifier: Framework :: Odoo
Classifier: License :: OSI Approved :: GNU Affero General Public License v3
Requires-Python: ~=2.7
Requires-Dist: odoo10-addon-base-transaction-id
Requires-Dist: odoo10-addon-sale-automatic-workflow-payment-mode
Requires-Dist: odoo (<10.1dev,>=10.0)
